webmetrics_api_client
