Metadata-Version: 1.1
Name: webmetrics-api-client
Version: 0.1.1
Summary: A simple client for interfacing with the Webmetrics API
Home-page: https://github.com/sbarbett/webmetrics_api_client
Author: Shane Barbetta
Author-email: shane@barbetta.me
License: GPL
Keywords: webmetrics_api_client
Platform: UNKNOWN
Classifier: Development Status :: 3 - Alpha
Classifier: Topic :: Utilities
Classifier: License :: OSI Approved :: BSD License
